Metadata-Version: 2.1
Name: system-data
Version: 1.0
Summary: A Python module that fetches system data and utilities.
Author: Ahson Shaikh
Author-email: ahsonshaikh616@gmail.com
